{
  "changedFilesIos": [
    "www\\scripts\\angular.js",
    "res\\icons\\android\\icon-72-hdpi.png",
    "res\\screens\\android\\screen-mdpi-landscape.png",
    "merges\\android\\scripts\\android2.3-jscompat.js",
    "merges\\windows\\scripts\\winstore-jscompat.js",
    "res\\icons\\ios\\icon-60.png",
    "plugins\\wp8.json",
    "res\\screens\\ios\\screen-iphone-landscape-736h.png",
    "res\\icons\\windows\\StoreLogo.scale-100.png",
    "www\\scripts\\index.js",
    "res\\icons\\android\\icon-48-mdpi.png",
    "www\\scripts\\angular-route.js",
    "res\\icons\\ios\\icon-72.png",
    "res\\icons\\ios\\icon-76.png",
    "res\\screens\\ios\\screen-ipad-portrait-2x.png",
    "plugins\\android.json",
    "res\\screens\\ios\\screen-iphone-portrait-2x.png",
    "res\\icons\\windows\\Square71x71Logo.scale-240.png",
    "merges\\android\\scripts\\platformOverrides.js",
    "www\\views\\page2.html",
    "res\\screens\\android\\screen-hdpi-portrait.png",
    "www\\css\\index.css",
    "res\\icons\\windows\\StoreLogo.scale-240.png",
    "plugins\\windows.json",
    "res\\screens\\ios\\screen-ipad-landscape.png",
    "www\\scripts\\angular.min.js.map",
    "packages.config",
    "res\\icons\\ios\\icon-60-3x.png",
    "config.xml",
    "res\\screens\\wp8\\SplashScreenImage.jpg",
    "www\\controllers\\Page2Ctrl.js",
    "www\\controllers\\Page1Ctrl.js",
    "res\\screens\\ios\\screen-ipad-landscape-2x.png",
    "res\\screens\\ios\\screen-iphone-568h-2x.png",
    "res\\icons\\windows\\Square150x150Logo.scale-100.png",
    "res\\screens\\android\\screen-ldpi-landscape.png",
    "res\\icons\\windows\\Wide310x150Logo.scale-240.png",
    "res\\icons\\windows\\Wide310x150Logo.scale-100.png",
    "res\\icons\\ios\\icon-72-2x.png",
    "res\\icons\\ios\\icon-76-2x.png",
    "www\\controllers\\HomeCtrl.js",
    "www\\scripts\\angular-mocks.js",
    "www\\scripts\\angular-route.min.js.map",
    "res\\icons\\ios\\icon-small.png",
    "res\\icons\\windows\\Square30x30Logo.scale-100.png",
    "www\\views\\home.html",
    "res\\icons\\wp8\\Background.png",
    "www\\index.html",
    "res\\icons\\ios\\icon-40.png",
    "res\\icons\\ios\\icon-60-2x.png",
    "res\\screens\\android\\screen-ldpi-portrait.png",
    "res\\native\\android\\ant.properties",
    "res\\icons\\windows\\Square310x310Logo.scale-100.png",
    "www\\scripts\\platformOverrides.js",
    "taco.json",
    "res\\icons\\windows\\Square150x150Logo.scale-240.png",
    "www\\scripts\\angular-route.min.js",
    "res\\icons\\android\\icon-36-ldpi.png",
    "merges\\windows\\scripts\\platformOverrides.js",
    "res\\screens\\ios\\screen-iphone-portrait.png",
    "Project_Readme.html",
    "res\\screens\\android\\screen-xhdpi-portrait.png",
    "res\\icons\\ios\\icon-50-2x.png",
    "res\\icons\\ios\\icon-57-2x.png",
    "res\\icons\\ios\\icon-50.png",
    "res\\icons\\ios\\icon-57.png",
    "res\\icons\\ios\\icon-small-2x.png",
    "res\\icons\\windows\\Square70x70Logo.scale-100.png",
    "res\\screens\\windows\\SplashScreen.scale-240.png",
    "www\\views\\page1.html",
    "res\\icons\\android\\icon-96-xhdpi.png",
    "res\\icons\\wp8\\ApplicationIcon.png",
    "res\\icons\\ios\\icon-40-2x.png",
    "res\\screens\\ios\\screen-iphone-portrait-667h.png",
    "res\\screens\\android\\screen-hdpi-landscape.png",
    "res\\screens\\windows\\SplashScreenPhone.scale-240.png",
    "www\\app.js",
    "res\\screens\\windows\\SplashScreen.scale-100.png",
    "res\\screens\\ios\\screen-iphone-portrait-736h.png",
    "res\\screens\\ios\\screen-ipad-portrait.png",
    "www\\scripts\\angular.min.js",
    "res\\screens\\android\\screen-xhdpi-landscape.png",
    "res\\icons\\windows\\Square44x44Logo.scale-240.png",
    "res\\screens\\android\\screen-mdpi-portrait.png",
    "Icon.png",
    "www\\Content\\bootstrap-theme.css.map",
    "www\\Content\\bootstrap.min.css",
    "www\\Scripts\\jquery-1.9.1.js",
    "www\\Content\\bootstrap-theme.css",
    "www\\Scripts\\bootstrap.js",
    "www\\Scripts\\bootstrap.min.js",
    "www\\fonts\\glyphicons-halflings-regular.eot",
    "www\\fonts\\glyphicons-halflings-regular.svg",
    "www\\fonts\\glyphicons-halflings-regular.ttf",
    "www\\Content\\bootstrap.css",
    "www\\fonts\\glyphicons-halflings-regular.woff2",
    "www\\Content\\bootstrap.css.map",
    "www\\Scripts\\jquery-1.9.1.min.js",
    "www\\Content\\bootstrap-theme.min.css",
    "www\\fonts\\glyphicons-halflings-regular.woff",
    "www\\Scripts\\jquery-1.9.1.min.map",
    "www\\Scripts\\jquery-1.9.1.intellisense.js",
    "www\\Scripts\\npm.js",
    "www\\services\\authService.js",
    "www\\controllers\\homectrl.js"
  ],
  "deletedFilesIos": [
    "Scripts\\jquery-1.9.1-vsdoc.js",
    "fonts\\glyphicons-halflings-regular.eot",
    "fonts\\glyphicons-halflings-regular.svg",
    "fonts\\glyphicons-halflings-regular.ttf",
    "Content\\bootstrap-theme.css",
    "Content\\bootstrap.css.map",
    "Scripts\\npm.js",
    "Scripts\\bootstrap.min.js",
    "Content\\bootstrap-theme.min.css",
    "Content\\bootstrap-theme.css.map",
    "Scripts\\bootstrap.js",
    "Content\\bootstrap.css",
    "fonts\\glyphicons-halflings-regular.woff",
    "Scripts\\jquery-1.9.1.intellisense.js",
    "Scripts\\jquery-1.9.1.js",
    "fonts\\glyphicons-halflings-regular.woff2",
    "Content\\bootstrap.min.css",
    "Scripts\\jquery-1.9.1.min.js",
    "Scripts\\jquery-1.9.1.min.map"
  ],
  "addedPluginsIos": [],
  "deletedPluginsIos": [],
  "changedFiles": [
    "plugins\\android.json"
  ],
  "deletedFiles": [],
  "addedPlugins": [],
  "deletedPlugins": []
}